prettymol/__init__.py
prettymol/cli.py
prettymol/color.py
prettymol/compositing.py
prettymol/core.py
prettymol/lighting.py
prettymol/materials.py
prettymol/molecule.py
prettymol/repltools.py
prettymol/selections.py
prettymol/styles.py
prettymol-0.3.1.dist-info/METADATA
prettymol-0.3.1.dist-info/WHEEL
prettymol-0.3.1.dist-info/entry_points.txt
prettymol-0.3.1.dist-info/RECORD
