Metadata-Version: 2.4
Name: prettymol
Version: 0.3.1
Summary: make molecules. pretty
Project-URL: Homepage, https://github.com/zachcp/prettymol
Project-URL: Issues, https://github.com/zachcp/prettymol/issues
Classifier: Development Status :: 3 - Alpha
Classifier: License :: OSI Approved :: MIT License
Classifier: Operating System :: OS Independent
Classifier: Programming Language :: Python :: 3
Requires-Python: ==3.11.*
Requires-Dist: biotite>=1.1
Requires-Dist: bpy
Requires-Dist: click
Requires-Dist: molecularnodes>=4.2.12
Requires-Dist: pillow
Provides-Extra: dev
Requires-Dist: pytest>=7.0; extra == 'dev'
